LICENSE.txt
setup.cfg
setup.py
Catalyst_Lib/UserProfile.py
Catalyst_Lib/__init__.py
Catalyst_Lib/colors.py
Catalyst_Lib/dictionaries.py
Catalyst_Lib/exporter.py
Catalyst_Lib/graphbuilder.py
Catalyst_Lib/htmlgen.py
Catalyst_Lib/lib.py
Catalyst_Lib/lists.py
Catalyst_Lib/multiLambda.py
Catalyst_Lib/progressBar.py
Catalyst_Lib/question.py
Catalyst_Lib/randomgen.py
Catalyst_Lib/table.py
Catalyst_Lib.egg-info/PKG-INFO
Catalyst_Lib.egg-info/SOURCES.txt
Catalyst_Lib.egg-info/dependency_links.txt
Catalyst_Lib.egg-info/requires.txt
Catalyst_Lib.egg-info/top_level.txt